github_logo.png
title_icon_python.png
pipupgui/__init__.py
pipupgui/__main__.py
pipupgui-0.5.2.dist-info/LICENSE
pipupgui-0.5.2.dist-info/METADATA
pipupgui-0.5.2.dist-info/WHEEL
pipupgui-0.5.2.dist-info/entry_points.txt
pipupgui-0.5.2.dist-info/top_level.txt
pipupgui-0.5.2.dist-info/RECORD
