Metadata-Version: 2.1
Name: pipupgui
Version: 0.5.2
Summary: GUI tool for installing and managing pip packages
Author-email: Dylan Taylor <dylan@shyapply.com>
License: MIT License
Project-URL: Homepage, https://github.com/Dylgod/pipupgui
Keywords: python,pip,package-manager,gui,development-tools
Classifier: Intended Audience :: Developers
Classifier: License :: OSI Approved :: MIT License
Classifier: Operating System :: Microsoft :: Windows
Classifier: Programming Language :: Python :: 3
Classifier: Programming Language :: Python :: 3.10
Classifier: Programming Language :: Python :: 3.11
Classifier: Programming Language :: Python :: 3.12
Classifier: Programming Language :: Python :: 3.13
Requires-Python: >=3.10
License-File: LICENSE
Requires-Dist: async-tkinter-loop>=0.9.3
Requires-Dist: customtkinter>=5.2.2
Requires-Dist: Pillow>=10.4.0
Requires-Dist: setuptools>=71.1.0
